[
    {
        "slug": "why-does-this-savage-grandma-never-flinch",
        "title": "Why Does This Savage Grandma Never Flinch?",
        "category_id": "22",
        "tags": [
            "Southern lifestyle",
            "Southern porch",
            "balls",
            "best comedy",
            "comedy",
            "comedy shorts",
            "comedy special",
            "comedy video",
            "cooter",
            "cozy atmosphere",
            "family moments",
            "floral dress",
            "funny",
            "golden hour",
            "grandmother",
            "jason martocci",
            "joke",
            "jokes",
            "martocci mayhem",
            "nature sounds",
            "nostalgia",
            "outdoor living",
            "peaceful scene",
            "porch life",
            "relaxation",
            "rocking chair",
            "savage grandma",
            "savage grandma jokes",
            "savage jokes",
            "shorts",
            "stand up comedy",
            "summer vibes",
            "sweet tea",
            "vintage style",
            "viral shorts",
            "warm colors"
        ]
    },
    {
        "slug": "how-ai-finds-the-best-parts-for-youtube-videos",
        "title": "How AI Finds the Best Parts for YouTube Videos!",
        "category_id": "24",
        "tags": [
            "Mukbang",
            "ASMR",
            "Food Review",
            "AI Mukbang",
            "Food Challenge",
            "Cake Decorating",
            "Food Science",
            "Creative Cooking",
            "Food Photography",
            "Cooking With AI",
            "Crystal Cake",
            "Eating Show",
            "Cake Design",
            "Food Experiments",
            "aismr",
            "asmr sounds",
            "viral shorts",
            "satisfying sounds",
            "asmr eating",
            "satisfying asmr",
            "satisfying video",
            "asmr food",
            "mukbang",
            "asmr mouth sounds",
            "asmr mukbang",
            "korean mukbang",
            "food asmr",
            "asmr video",
            "satisfying videos",
            "asmr sleep",
            "asmr roleplay",
            "asmr massage",
            "asmr no talking"
        ]
    },
    {
        "slug": "what-happens-when-you-cut-objects-in-reverse-asmr",
        "title": "What Happens When You Cut Objects in REVERSE ASMR",
        "category_id": "24",
        "tags": [
            "Jason Martocci",
            "Martocci Mayhem",
            "Viral Video",
            "Relaxing Video",
            "Amazing Videos",
            "AI ASMR",
            "ASMR",
            "satisfying video",
            "entertainment",
            "satisfying",
            "chaos",
            "reverse",
            "compilation",
            "hot knives",
            "reassembling",
            "mesmerizing",
            "destruction",
            "visual satisfaction",
            "mayhem reversed",
            "asmr cutting",
            "relaxing videos",
            "satisfying videos",
            "asmr video",
            "visual asmr",
            "ai cutting asmr",
            "cutting asmr",
            "asmr ai",
            "asmr videos",
            "ai",
            "rewind",
            "asmr shorts",
            "reverse asmr",
            "asmr in reverse",
            "asmr reversed",
            "superheated knife",
            "knife",
            "aismr"
        ]
    },
    {
        "slug": "experience-satisfying-sounds-of-slicing-open-glass-dragon-fruit-asmr",
        "title": "EXPERIENCE Satisfying Sounds of Slicing Open GLASS Dragon Fruit ASMR!",
        "category_id": "24",
        "tags": [
            "oddly satisfying",
            "youtube shorts",
            "trending now",
            "asmr",
            "ASMR",
            "nature sounds",
            "cooking ASMR",
            "glass fruit cutting",
            "satisfying video",
            "food ASMR",
            "relaxation",
            "glass cutting",
            "healthy eating",
            "satisfying",
            "sound therapy",
            "visual ASMR",
            "fruit cutting asmr",
            "unboxing video",
            "satisfying videos",
            "dragon fruit",
            "glass dragon fruit",
            "fruit slicing",
            "sensory experience",
            "google veo 3",
            "oddly satisfying video",
            "ai asmr",
            "asmr shorts",
            "satisfying sounds",
            "cutting asmr",
            "asmr sounds",
            "relaxing sounds",
            "ai"
        ]
    },
    {
        "slug": "why-i-quit-drinking-but-still-mess-up",
        "title": "Why I Quit Drinking But Still Mess Up!",
        "desc": "Get ready for a dose of sassy grandma wisdom! In this hilarious video, we're counting down the savagiest grandma jokes EVER! From family moments that ...",
        "category_id": "22",
        "tags": [
            "tiktok",
            "Comedy",
            "Funny jokes",
            "Dark humor",
            "Humor",
            "Hilarious",
            "Savage jokes",
            "Entertaining content",
            "Savage humor",
            "One-liners",
            "Funny grandma",
            "Sarcastic humor",
            "Stand-up comedy",
            "Jokes for adults",
            "Comedic videos",
            "Viral jokes",
            "Roast jokes",
            "Grandma jokes",
            "Family jokes",
            "Meme jokes",
            "comedy video",
            "ranking humor jokes",
            "top dark humor jokes",
            "comedy videos",
            "stand up comedy",
            "funny",
            "best comedy",
            "comedy shorts",
            "funny dark humor jokes",
            "stand up",
            "dark humor jokes",
            "comedy show",
            "funny dark jokes"
        ],
        "video_id": "Mde2TglHZSA"
    },
    {
        "slug": "what-happens-when-you-stop-drinking",
        "title": "What Happens When You Stop Drinking?",
        "desc": "Get ready to laugh out loud with the most savage grandma jokes ever! In this hilarious video, we bring you the perfect blend of grandma wisdom and a s...",
        "category_id": "22",
        "tags": [
            "funny videos",
            "tiktok",
            "comedy",
            "funny jokes",
            "dark humor",
            "humor",
            "hilarious",
            "best jokes",
            "comedy skits",
            "joke of the day",
            "savage jokes",
            "savage humor",
            "savage memes",
            "funny grandma",
            "stand-up comedy",
            "roast jokes",
            "viral jokes",
            "grandma humor",
            "grandma jokes",
            "joke compilation",
            "comedians",
            "funny",
            "stand up",
            "stand up comedy",
            "humorous",
            "dad jokes",
            "comedy central",
            "stand up comedy full",
            "best stand up",
            "the comedy store",
            "comedy videos",
            "funny video",
            "comedy video",
            "stand up routine",
            "stand up comedian"
        ],
        "video_id": "JWjlWFO30b0"
    },
    {
        "slug": "50-seconds-of-pure-magic-with-9-second-asmr-clips",
        "title": "50 Seconds of PURE MAGIC with 9-Second ASMR Clips!",
        "desc": "Get ready for a mesmerizing experience! In this unique video, we're mixing magic in 50 seconds using 9-second ASMR clips! Immerse yourself in this rel...",
        "category_id": "24",
        "tags": [
            "meditation",
            "ASMR",
            "ambient sound",
            "stress relief",
            "visuals",
            "audio",
            "relaxation",
            "chillout",
            "calming sounds",
            "peaceful",
            "sound therapy",
            "soothing",
            "ASMR video",
            "tranquil",
            "short videos",
            "sensory experience",
            "mix and mash",
            "weekly highlights",
            "soothing music",
            "stress relief music",
            "reep sleeping music",
            "soothing relaxation",
            "meditation music",
            "peaceful music",
            "relaxing music",
            "piano",
            "smoothing relaxation",
            "sleeping music",
            "meditation for anxiety",
            "dream music",
            "sleep music",
            "relaxing music to sleep",
            "piano music"
        ],
        "video_id": "kLcmQWQKy98"
    },
    {
        "slug": "mixing-this-week-s-best-9-second-asmr-clips-into-50-seconds-of-bliss",
        "title": "Mixing THIS WEEK'S BEST 9-Second ASMR Clips into 50 Seconds of Bliss?",
        "desc": "Get ready to relax with the most calming ASMR experience! In this video, we've curated the best 9-second ASMR clips of the week and mixed them into 50...",
        "category_id": "24",
        "tags": [
            "meditation",
            "ASMR",
            "ambient sounds",
            "stress relief",
            "calming videos",
            "relaxation",
            "soothing sounds",
            "ASMR triggers",
            "sound therapy",
            "short form content",
            "short videos",
            "sensory experience",
            "audio mixes",
            "creative mixes",
            "ASMR community",
            "video compilation",
            "weekly highlights",
            "soothing relaxation",
            "calm music",
            "deep sleep",
            "stress relief music",
            "meditation music",
            "asmr sleep",
            "stress",
            "sound bath",
            "ambiance",
            "sleeping",
            "sleep music",
            "ai",
            "aiasmr",
            "asmr sounds",
            "asmr visuals",
            "no talking asmr",
            "relaxing",
            "piano"
        ],
        "video_id": "QgfRY7elfQg"
    }
]